CHANGES.rst
DESCRIPTION.rst
LICENSE
MANIFEST.in
README.md
setup.py
src/happy/logo.png
src/happy/base/__init__.py
src/happy/base/app.py
src/happy/base/class_lister.py
src/happy/base/config.py
src/happy/base/core.py
src/happy/base/registry.py
src/happy/console/__init__.py
src/happy/console/ann_to_happy/__init__.py
src/happy/console/ann_to_happy/generate.py
src/happy/console/builders/__init__.py
src/happy/console/builders/generic_regression_build.py
src/happy/console/builders/generic_unsupervised_build.py
src/happy/console/builders/regression_build.py
src/happy/console/builders/segmentation_build.py
src/happy/console/builders/unsupervised_build.py
src/happy/console/happy_splitter/__init__.py
src/happy/console/happy_splitter/split.py
src/happy/console/hdr_info/__init__.py
src/happy/console/hdr_info/output.py
src/happy/console/help/__init__.py
src/happy/console/help/generate.py
src/happy/console/hsi_to_rgb/__init__.py
src/happy/console/hsi_to_rgb/generate.py
src/happy/console/image_regions_objects/__init__.py
src/happy/console/image_regions_objects/generate.py
src/happy/console/mat_info/__init__.py
src/happy/console/mat_info/output.py
src/happy/console/opex_labels/__init__.py
src/happy/console/opex_labels/generate.py
src/happy/console/plot_preproc/__init__.py
src/happy/console/plot_preproc/output.py
src/happy/console/process_data/__init__.py
src/happy/console/process_data/process.py
src/happy/console/raw_check/__init__.py
src/happy/console/raw_check/process.py
src/happy/console/sub_images/__init__.py
src/happy/console/sub_images/generate.py
src/happy/criteria/__init__.py
src/happy/criteria/_criteria.py
src/happy/data/__init__.py
src/happy/data/_core.py
src/happy/data/_datamanager.py
src/happy/data/_envi_settings.py
src/happy/data/_happy_data.py
src/happy/data/_mask_labels.py
src/happy/data/_sample_id_handler.py
src/happy/data/_sub_images.py
src/happy/data/annotations/__init__.py
src/happy/data/annotations/_contours.py
src/happy/data/annotations/_markers.py
src/happy_tools_core.egg-info/PKG-INFO
src/happy_tools_core.egg-info/SOURCES.txt
src/happy_tools_core.egg-info/dependency_links.txt
src/happy_tools_core.egg-info/entry_points.txt
src/happy_tools_core.egg-info/requires.txt
src/happy_tools_core.egg-info/top_level.txt